archappl/__init__.py
archappl/admin/__init__.py
archappl/admin/client.py
archappl/client/__init__.py
archappl/config/__init__.py
archappl/config/default.ini
archappl/contrib/__init__.py
archappl/contrib/data.py
archappl/contrib/mgmt.py
archappl/data/__init__.py
archappl/data/client.py
archappl/data/utils.py
archappl/data/pb/EPICSEvent_pb2.py
archappl/data/pb/__init__.py
archappl/data/pb/decode.py
archappl/scripts/__init__.py
archappl/scripts/get.py
archappl/scripts/inspect.py
archappl/scripts/utils.py
archappl/tests/conftest.py
archappl/tests/test_config.py
archappl/tests/test_data_client.py
archappl/tests/test_datetime.py
archappl/tests/test_mgmt_client.py
pyarchappl-1.0.3.post1.dist-info/licenses/LICENSE
pyarchappl-1.0.3.post1.dist-info/METADATA
pyarchappl-1.0.3.post1.dist-info/WHEEL
pyarchappl-1.0.3.post1.dist-info/entry_points.txt
pyarchappl-1.0.3.post1.dist-info/top_level.txt
pyarchappl-1.0.3.post1.dist-info/RECORD
