Metadata-Version: 2.4
Name: pyarchappl
Version: 1.0.3.post1
Summary: Python interface to Archiver Appliance
Home-page: https://github.com/zhangt58/pyarchappl
Author: Tong Zhang
Project-URL: Homepage, https://github.com/zhangt58/pyarchappl
Project-URL: PyPI, https://pypi.org/project/pyarchappl
Keywords: Archiver,EPICS,CA,PVA
Classifier: Programming Language :: Python :: 3
Classifier: Programming Language :: Python :: 3.9
Classifier: Programming Language :: Python :: 3.10
Classifier: Programming Language :: Python :: 3.11
Classifier: Programming Language :: Python :: 3.12
Classifier: Programming Language :: Python :: 3.13
Classifier: Topic :: Scientific/Engineering
Classifier: Topic :: Software Development :: Libraries :: Python Modules
Requires-Python: >=3.9
License-File: LICENSE
Requires-Dist: numpy
Requires-Dist: pandas
Requires-Dist: openpyxl
Requires-Dist: tqdm
Requires-Dist: requests
Requires-Dist: simplejson
Requires-Dist: tables
Requires-Dist: protobuf<4.0,>=3.0
Requires-Dist: setuptools
Provides-Extra: test
Requires-Dist: pytest; extra == "test"
Provides-Extra: doc
Requires-Dist: sphinx; extra == "doc"
Requires-Dist: pydata_sphinx_theme; extra == "doc"
Dynamic: home-page
Dynamic: license-file
Dynamic: requires-python
